handyderivatives/__init__.py
handyderivatives-2.3.2.dist-info/entry_points.txt
handyderivatives-2.3.2.dist-info/LICENSE
handyderivatives-2.3.2.dist-info/WHEEL
handyderivatives-2.3.2.dist-info/METADATA
handyderivatives-2.3.2.dist-info/RECORD
