Metadata-Version: 2.1
Name: handyderivatives
Version: 2.3.2
Summary: Calc. on the command line - with LaTeX output.
Home-page: https://github.com/fitzy1293/handyderivatives
License: MIT
Author: fitzy1293
Requires-Python: >=3.6,<4.0
Classifier: License :: OSI Approved :: MIT License
Classifier: Programming Language :: Python :: 3
Classifier: Programming Language :: Python :: 3.6
Classifier: Programming Language :: Python :: 3.7
Classifier: Programming Language :: Python :: 3.8
Requires-Dist: sympy (>=1.7.1,<2.0.0)
Project-URL: Repository, https://github.com/fitzy1293/handyderivatives
